AUTHORS.rst
CONTRIBUTING.rst
HISTORY.rst
LICENSE
MANIFEST.in
README.rst
setup.cfg
setup.py
bygfiles/__init__.py
bygfiles/commands.py
bygfiles/conf.py
bygfiles/default_settings.py
bygfiles/server.py
bygfiles.egg-info/PKG-INFO
bygfiles.egg-info/SOURCES.txt
bygfiles.egg-info/dependency_links.txt
bygfiles.egg-info/entry_points.txt
bygfiles.egg-info/not-zip-safe
bygfiles.egg-info/requires.txt
bygfiles.egg-info/top_level.txt
bygfiles/storages/__init__.py
bygfiles/storages/core.py
bygfiles/storages/diskstorage.py
bygfiles/storages/s3storage.py
docs/Makefile
docs/authors.rst
docs/conf.py
docs/contributing.rst
docs/history.rst
docs/index.rst
docs/installation.rst
docs/make.bat
docs/readme.rst
docs/usage.rst
pyfiles/__init__.py
pyfiles/commands.py
pyfiles/conf.py
pyfiles/default_settings.py
pyfiles/server.py
pyfiles/storages/__init__.py
pyfiles/storages/core.py
pyfiles/storages/diskstorage.py
pyfiles/storages/s3storage.py
tests/test_pyfiles.py
tests/workingdir/settings_disk.py
tests/workingdir/settings_s3.py