Metadata-Version: 1.1
Name: bygfiles
Version: 0.1.1
Summary: Big file collection manager
Home-page: https://github.com/jrmi/pyfiles
Author: Jeremie Pardou
Author-email: jpardou@makina-corpus.com
License: MIT license
Keywords: store storage api cli big files
Platform: UNKNOWN
Classifier: Development Status :: 4 - Beta
Classifier: Intended Audience :: Developers
Classifier: License :: OSI Approved :: MIT License
Classifier: Natural Language :: English
Classifier: Programming Language :: Python :: 2
Classifier: Programming Language :: Python :: 2.7
Classifier: Programming Language :: Python :: 3
Classifier: Programming Language :: Python :: 3.4
Classifier: Programming Language :: Python :: 3.5
Classifier: Programming Language :: Python :: 3.6
Classifier: Programming Language :: Python :: 3.7
